<?xml version="1.0" encoding="utf-8" ?><dwsync><file name="ajax-en.html" server="Macintosh HD 2 2 1/WebFiles/WET.TestProject/" local="3482152024" remote="-4611808318433956776" Dst="-1" /><file name="ajax-fr.html" server="Macintosh HD 2 2 1/WebFiles/WET.TestProject/" local="3482152024" remote="-4611808318433956776" Dst="-1" /><file name="ajax1-en.html" server="Macintosh HD 2 2 1/WebFiles/WET.TestProject/" local="3482152024" remote="-4611808318433956776" Dst="-1" /><file name="ajax1-fr.html" server="Macintosh HD 2 2 1/WebFiles/WET.TestProject/" local="3482152024" remote="-4611808318433956776" Dst="-1" /><file name="ajax2-en.html" server="Macintosh HD 2 2 1/WebFiles/WET.TestProject/" local="3482152024" remote="-4611808318433956776" Dst="-1" /><file name="ajax2-fr.html" server="Macintosh HD 2 2 1/WebFiles/WET.TestProject/" local="3482152024" remote="-4611808318433956776" Dst="-1" /><file name="ajax3-en.html" server="Macintosh HD 2 2 1/WebFiles/WET.TestProject/" local="3482152024" remote="-4611808318433956776" Dst="-1" /><file name="ajax3-fr.html" server="Macintosh HD 2 2 1/WebFiles/WET.TestProject/" local="3482152023" remote="-4611808318433956777" Dst="-1" /></dwsync>